LICENSE
README.md
setup.py
chatinterface_client/__init__.py
chatinterface_client/__main__.py
chatinterface_client/config.py
chatinterface_client/cui.py
chatinterface_client/gui.py
chatinterface_client/version.py
chatinterface_client/interfaces/__init__.py
chatinterface_client/interfaces/loginstore.py
chatinterface_client/interfaces/route_clients.py
chatinterface_client/interfaces/ws.py
newguy103_chatinterface_client.egg-info/PKG-INFO
newguy103_chatinterface_client.egg-info/SOURCES.txt
newguy103_chatinterface_client.egg-info/dependency_links.txt
newguy103_chatinterface_client.egg-info/requires.txt
newguy103_chatinterface_client.egg-info/top_level.txt