Metadata-Version: 2.1
Name: newguy103-chatinterface-client
Version: 0.0.1
Summary: Client for chatinterface-server.
Author: NewGuy103
Author-email: userchouenthusiast@gmail.com
License: GPL v3.0
License-File: LICENSE
Requires-Dist: platformdirs
Requires-Dist: pyside6
Requires-Dist: websockets
Requires-Dist: msgpack
Requires-Dist: qasync
Requires-Dist: httpx
Requires-Dist: keyring
